spdx_lint/__init__.py
spdx_lint/__main__.py
spdx_lint/cli.py
spdx_lint/lint.py
spdx_lint-2023.10.22.dist-info/LICENSE
spdx_lint-2023.10.22.dist-info/METADATA
spdx_lint-2023.10.22.dist-info/WHEEL
spdx_lint-2023.10.22.dist-info/entry_points.txt
spdx_lint-2023.10.22.dist-info/top_level.txt
spdx_lint-2023.10.22.dist-info/RECORD
