Metadata-Version: 2.1
Name: spdx-lint
Version: 2023.10.22
Summary: Experimental SPDX baseline validator.
Author-email: Stefan Hagen <stefan@hagen.link>
Maintainer-email: Stefan Hagen <stefan@hagen.link>
Project-URL: Homepage, https://git.sr.ht/~sthagen/spdx-lint
Project-URL: Bug-Tracker, https://todo.sr.ht/~sthagen/spdx-lint
Project-URL: Documentation, https://codes.dilettant.life/docs/spdx-lint
Project-URL: Source-Code, https://git.sr.ht/~sthagen/spdx-lint
Project-URL: Test-Coverage, https://codes.dilettant.life/coverage/spdx-lint
Keywords: baseline,developer-tools,extension,software-bill-of-materials,spdx,validation
Classifier: Development Status :: 3 - Alpha
Classifier: Intended Audience :: Developers
Classifier: License :: OSI Approved :: MIT License
Classifier: Programming Language :: Python :: 3.10
Classifier: Programming Language :: Python :: 3.11
Classifier: Programming Language :: Python :: 3.12
Classifier: Programming Language :: Python :: 3.9
Requires-Python: >=3.9
License-File: LICENSE
Requires-Dist: jsonschema >=4.19.1
Requires-Dist: typer >=0.9.0
Requires-Dist: xmlschema >=2.5.0
Provides-Extra: dev
Requires-Dist: black ; extra == 'dev'
Requires-Dist: coverage ; extra == 'dev'
Requires-Dist: hypothesis ; extra == 'dev'
Requires-Dist: mypy ; extra == 'dev'
Requires-Dist: pytest ; extra == 'dev'
Requires-Dist: pytest-cov ; extra == 'dev'
Requires-Dist: pytest-flake8 ; extra == 'dev'
Requires-Dist: ruff ; extra == 'dev'
